LICENSE
README.md
setup.py
ewia/ApparentPosition.py
ewia/DataPrinter.py
ewia/EquatorialCoordObject.py
ewia/FriendlyArgumentParser.py
ewia/ObjectCatalog.py
ewia/Observer.py
ewia/OrbitalElements.py
ewia/SunObject.py
ewia/Time.py
ewia/Tools.py
ewia/VectorR3.py
ewia/__init__.py
ewia/__main__.py
ewia.egg-info/PKG-INFO
ewia.egg-info/SOURCES.txt
ewia.egg-info/dependency_links.txt
ewia.egg-info/entry_points.txt
ewia.egg-info/requires.txt
ewia.egg-info/top_level.txt
ewia/tests/EquatorialCoordTests.py
ewia/tests/ObserverTests.py
ewia/tests/OrbitalElementsTests.py
ewia/tests/TimeTests.py
ewia/tests/TrivialTests.py
ewia/tests/__init__.py