Metadata-Version: 2.1
Name: ewia
Version: 0.0.2
Summary: A library to calculate astrophysical object positions
Home-page: https://github.com/johndoe31415/ewia
Download-URL: https://github.com/johndoe31415/ewia/archive/v0.0.2.tar.gz
Author: Johannes Bauer
Author-email: joe@johannes-bauer.com
License: gpl-3.0
Keywords: astrophysics,calculator,position,deep-sky,ephemeris,planets
Classifier: Development Status :: 5 - Production/Stable
Classifier: Intended Audience :: Developers
Classifier: License :: OSI Approved :: GNU General Public License v3 (GPLv3)
Classifier: Programming Language :: Python :: 3
Classifier: Programming Language :: Python :: 3 :: Only
Classifier: Programming Language :: Python :: 3.10
Classifier: Programming Language :: Python :: 3.11
Classifier: Programming Language :: Python :: 3.10
License-File: LICENSE
Requires-Dist: pytz
